q_store-4.1.1.dist-info/RECORD
q_store-4.1.1.dist-info/WHEEL
q_store-4.1.1.dist-info/top_level.txt
q_store-4.1.1.dist-info/METADATA
q_store-4.1.1.dist-info/LICENCE
q_store/constants.c
q_store/constants.cpython-312-darwin.so
q_store/__init__.py
q_store/exceptions.c
q_store/exceptions.cpython-312-darwin.so
q_store/visualization/state_visualizer.c
q_store/visualization/state_visualizer.cpython-312-darwin.so
q_store/visualization/utils.cpython-312-darwin.so
q_store/visualization/__init__.py
q_store/visualization/utils.c
q_store/visualization/circuit_visualizer.cpython-312-darwin.so
q_store/visualization/circuit_visualizer.c
q_store/kernels/fidelity_kernel.c
q_store/kernels/quantum_kernel.c
q_store/kernels/trainable_kernel.cpython-312-darwin.so
q_store/kernels/projected_kernel.cpython-312-darwin.so
q_store/kernels/trainable_kernel.c
q_store/kernels/__init__.py
q_store/kernels/projected_kernel.c
q_store/kernels/quantum_kernel.cpython-312-darwin.so
q_store/kernels/fidelity_kernel.cpython-312-darwin.so
q_store/tomography/process_tomography.c
q_store/tomography/process_tomography.cpython-312-darwin.so
q_store/tomography/__init__.py
q_store/tomography/state_tomography.cpython-312-darwin.so
q_store/tomography/state_tomography.c
q_store/embeddings/basis_encoding.c
q_store/embeddings/angle_encoding.cpython-312-darwin.so
q_store/embeddings/feature_maps.cpython-312-darwin.so
q_store/embeddings/__init__.py
q_store/embeddings/feature_maps.c
q_store/embeddings/angle_encoding.c
q_store/embeddings/amplitude_encoding.c
q_store/embeddings/amplitude_encoding.cpython-312-darwin.so
q_store/embeddings/basis_encoding.cpython-312-darwin.so
q_store/core/circuit_converters.cpython-312-darwin.so
q_store/core/circuit_optimizer.cpython-312-darwin.so
q_store/core/tunneling_engine.cpython-312-darwin.so
q_store/core/circuit_converters.c
q_store/core/entanglement_registry.c
q_store/core/entanglement_registry.cpython-312-darwin.so
q_store/core/state_manager.c
q_store/core/__init__.py
q_store/core/unified_circuit.c
q_store/core/circuit_optimizer.c
q_store/core/state_manager.cpython-312-darwin.so
