Metadata-Version: 2.2
Name: q-store
Version: 4.1.1
Summary: Quantum-First Machine Learning Framework with Async Execution and Production Storage
Author-email: Yucel Zengin <yucelz@gmail.com>
Maintainer-email: Yucel Zengin <yucelz@gmail.com>
License: AGPL-3.0-or-later
Project-URL: Homepage, http://www.q-store.tech
Project-URL: Documentation, https://github.com/yucelz/q-store/tree/main/docs
Project-URL: Repository, https://github.com/yucelz/q-store
Project-URL: Issues, https://github.com/yucelz/q-store/issues
Keywords: quantum,database,vector-search,quantum-computing,ionq,superposition,entanglement
Classifier: Development Status :: 4 - Beta
Classifier: Intended Audience :: Developers
Classifier: Intended Audience :: Science/Research
Classifier: Topic :: Database
Classifier: Topic :: Scientific/Engineering :: Physics
Classifier: Programming Language :: Python :: 3
Classifier: Programming Language :: Python :: 3.11
Classifier: Programming Language :: Python :: 3.12
Classifier: Programming Language :: Python :: 3.13
Classifier: Programming Language :: Cython
Classifier: Operating System :: OS Independent
Classifier: Typing :: Typed
Requires-Python: >=3.11
License-File: LICENCE
Requires-Dist: numpy<3.0.0,>=1.24.0
Requires-Dist: scipy>=1.10.0
Requires-Dist: cirq>=1.3.0
Requires-Dist: cirq-ionq>=1.3.0
Requires-Dist: requests>=2.31.0
Requires-Dist: zarr>=2.16.0
Requires-Dist: pyarrow>=14.0.0
Requires-Dist: aiohttp>=3.9.0
Requires-Dist: pandas>=2.0.0
Requires-Dist: scikit-learn>=1.3.0
Requires-Dist: pillow>=10.0.0
Requires-Dist: h5py>=3.9.0
Provides-Extra: backends
Requires-Dist: pinecone>=3.0.0; extra == "backends"
Requires-Dist: pgvector>=0.2.0; extra == "backends"
Requires-Dist: qdrant-client>=1.7.0; extra == "backends"
Provides-Extra: ml
Requires-Dist: torch>=2.0.0; extra == "ml"
Requires-Dist: tensorflow>=2.13.0; extra == "ml"
Provides-Extra: storage
Requires-Dist: zarr>=2.16.0; extra == "storage"
Requires-Dist: pyarrow>=14.0.0; extra == "storage"
Requires-Dist: aiohttp>=3.9.0; extra == "storage"
Requires-Dist: pandas>=2.0.0; extra == "storage"
Provides-Extra: datasets
Requires-Dist: datasets>=2.14.0; extra == "datasets"
Requires-Dist: huggingface-hub>=0.17.0; extra == "datasets"
Provides-Extra: augmentation
Requires-Dist: albumentations>=1.3.0; extra == "augmentation"
Requires-Dist: opencv-python>=4.8.0; extra == "augmentation"
Provides-Extra: tracking
Requires-Dist: mlflow>=2.7.0; extra == "tracking"
Requires-Dist: tensorboard>=2.14.0; extra == "tracking"
Requires-Dist: wandb>=0.15.0; extra == "tracking"
Provides-Extra: tuning
Requires-Dist: optuna>=3.3.0; extra == "tuning"
Requires-Dist: bayesian-optimization>=1.4.0; extra == "tuning"
Provides-Extra: build
Requires-Dist: Cython>=0.29.0; extra == "build"
Requires-Dist: wheel; extra == "build"
Requires-Dist: twine; extra == "build"
Provides-Extra: dev
Requires-Dist: pytest>=7.0.0; extra == "dev"
Requires-Dist: pytest-asyncio>=0.21.0; extra == "dev"
Requires-Dist: pytest-cov>=4.0.0; extra == "dev"
Requires-Dist: black>=23.0.0; extra == "dev"
Requires-Dist: ruff>=0.1.0; extra == "dev"
Requires-Dist: isort>=5.12.0; extra == "dev"
Requires-Dist: mypy>=1.0.0; extra == "dev"
Requires-Dist: pre-commit>=3.0.0; extra == "dev"
Provides-Extra: docs
Requires-Dist: sphinx>=5.0.0; extra == "docs"
Requires-Dist: sphinx-rtd-theme>=1.2.0; extra == "docs"
Requires-Dist: sphinx-autodoc-typehints>=1.23.0; extra == "docs"
Provides-Extra: all
Requires-Dist: q-store[augmentation,backends,datasets,dev,docs,ml,storage,tracking,tuning]; extra == "all"
Dynamic: requires-python
